_petsc_miner.cpython-312-x86_64-linux-gnu.so
petsc_ts/__init__.py
petsc_ts/classifier.py
petsc_ts/pets.py
petsc_ts/preprocessing.py
petsc_ts/sax.py
petsc_ts-1.4.dist-info/METADATA
petsc_ts-1.4.dist-info/WHEEL
petsc_ts-1.4.dist-info/top_level.txt
petsc_ts-1.4.dist-info/RECORD
petsc_ts-1.4.dist-info/licenses/LICENSE
