Metadata-Version: 2.4
Name: petsc_ts
Version: 1.4
Summary: Pattern-based Embedding for Time Series Classification
Author-email: Len Feremans <len.feremans@gmail.com>
Maintainer-email: "Stijn J. Rotman" <s.j.rotman@uvt.nl>
License-Expression: MIT
Requires-Python: >=3.9
License-File: LICENSE
Requires-Dist: numpy
Requires-Dist: scipy
Requires-Dist: scikit-learn
Requires-Dist: aeon
Requires-Dist: sax-ts
Provides-Extra: test
Requires-Dist: pytest; extra == "test"
Provides-Extra: examples
Requires-Dist: matplotlib; extra == "examples"
Dynamic: license-file
